{
  "curso": "Direito - Integral",
  "curso_pasta": "direito_-_integral",
  "periodo": 4,
  "modelo": "Comite_Arvores_XGB_LGBM_CatBoost",
  "melhor_repeticao": 20,
  "threshold": 0.21071812000578785,
  "acuracia": 0.9227272727272727,
  "f1_weighted": 0.9255723352497547,
  "f1_pos": 0.5405405405405406,
  "roc_auc": 0.8416401043175891,
  "avg_precision": 0.4599596821219901,
  "brier_pre": 0.08687557227861391,
  "brier_cal": 0.05305305625716766,
  "features": [
    "nota_ingresso",
    "tipo_ingresso_pism",
    "tipo_ingresso_sisu",
    "tipo_ingresso_vestibular",
    "tipo_ingresso_outros",
    "cota_racial",
    "cota_ampla_concorrencia",
    "cota_escola_publica",
    "cota_renda",
    "cota_pcd",
    "genero_masculino",
    "genero_feminino",
    "genero_outros",
    "periodo_1_disciplinas_aprovadas",
    "periodo_1_disciplinas_reprovadas",
    "periodo_1_disciplinas_ri",
    "periodo_1_disciplinas_trancadas",
    "periodo_1_disciplinas_outros_status",
    "periodo_1_bolsa_remunerada",
    "periodo_1_bolsa_n_remunerada",
    "periodo_1_ae",
    "periodo_2_disciplinas_aprovadas",
    "periodo_2_disciplinas_reprovadas",
    "periodo_2_disciplinas_ri",
    "periodo_2_disciplinas_trancadas",
    "periodo_2_disciplinas_outros_status",
    "periodo_2_bolsa_remunerada",
    "periodo_2_bolsa_n_remunerada",
    "periodo_2_ae",
    "periodo_3_disciplinas_aprovadas",
    "periodo_3_disciplinas_reprovadas",
    "periodo_3_disciplinas_ri",
    "periodo_3_disciplinas_trancadas",
    "periodo_3_disciplinas_outros_status",
    "periodo_3_bolsa_remunerada",
    "periodo_3_bolsa_n_remunerada",
    "periodo_3_ae",
    "periodo_4_disciplinas_aprovadas",
    "periodo_4_disciplinas_reprovadas",
    "periodo_4_disciplinas_ri",
    "periodo_4_disciplinas_trancadas",
    "periodo_4_disciplinas_outros_status",
    "periodo_4_bolsa_remunerada",
    "periodo_4_bolsa_n_remunerada",
    "periodo_4_ae",
    "etnia_branca",
    "etnia_outra",
    "etnia_parda",
    "etnia_preta"
  ],
  "pesos": [
    0.2915451895040862,
    0.31486880466441314,
    0.39358600583051645
  ]
}